<annotation>
	<folder>images</folder>
	<filename>frame (2289).png</filename>
	<path>/images/frame (2289).png</path>
	<source>
		<database>Unspecified</database>
	</source>
	<size>
		<width>240</width>
		<height>240</height>
		<depth>3</depth>
	</size>
	<object>
		<name>A</name>
		<pose>Unspecified</pose>
		<truncated>Unspecified</truncated>
		<difficult>Unspecified</difficult>
		<bndbox>
			<xmin>57</xmin>
			<ymin>90</ymin>
			<xmax>202</xmax>
			<ymax>226</ymax>
		</bndbox>
	</object>
</annotation>